setup.py
browser_profile_cookies.egg-info/PKG-INFO
browser_profile_cookies.egg-info/SOURCES.txt
browser_profile_cookies.egg-info/dependency_links.txt
browser_profile_cookies.egg-info/requires.txt
browser_profile_cookies.egg-info/top_level.txt
profile_cookies/__init__.py
profile_cookies/__version__.py
profile_cookies/paths.py